s5a/__init__.py
tests/__init__.py
s5a-0.4.dist-info/LICENSE
s5a-0.4.dist-info/METADATA
s5a-0.4.dist-info/WHEEL
s5a-0.4.dist-info/top_level.txt
s5a-0.4.dist-info/RECORD
