Metadata-Version: 2.1
Name: s5a
Version: 0.4
Summary: Sentinel-5 Algorithms
Home-page: https://github.com/emissions-api/sentinel5algorithms
Author: Emissions API Developers
License: MIT
Platform: UNKNOWN
Classifier: Development Status :: 3 - Alpha
Classifier: Intended Audience :: Developers
Classifier: License :: OSI Approved :: MIT License
Classifier: Programming Language :: Python :: 3
Classifier: Programming Language :: Python :: 3.6
Classifier: Programming Language :: Python :: 3.7
Classifier: Operating System :: OS Independent
Classifier: Topic :: Scientific/Engineering :: GIS
Requires-Dist: h3
Requires-Dist: netCDF4
Requires-Dist: numpy
Requires-Dist: pandas
